Metadata-Version: 2.1
Name: mmps
Version: 2.4.0
Summary: OpenMMLab Detection Toolbox and Benchmark
Home-page: https://github.com/open-mmlab/mmdetection
Author: OpenMMLab
Author-email: openmmlab@gmail.com
License: Apache License 2.0
Keywords: computer vision,object detection
Platform: UNKNOWN
Classifier: Development Status :: 5 - Production/Stable
Classifier: License :: OSI Approved :: Apache Software License
Classifier: Operating System :: OS Independent
Classifier: Programming Language :: Python :: 3
Classifier: Programming Language :: Python :: 3.6
Classifier: Programming Language :: Python :: 3.7
Classifier: Programming Language :: Python :: 3.8
Provides-Extra: all
Provides-Extra: tests
Provides-Extra: build
Provides-Extra: optional
